LensToZotero/LensToZotero.py
LensToZotero/__init__.py
LensToZotero/utils.py
LensToZotero-0.1.4.dist-info/LICENSE
LensToZotero-0.1.4.dist-info/METADATA
LensToZotero-0.1.4.dist-info/WHEEL
LensToZotero-0.1.4.dist-info/top_level.txt
LensToZotero-0.1.4.dist-info/RECORD
