Metadata-Version: 2.1
Name: LensToZotero
Version: 0.1.4
Summary: A package to transfer Lens publications in csv format to Zotero
Home-page: https://github.com/RIEPPfunction/LensToZotero
Author: Kostuk Danill
Author-email: kostukml@gmail.com
Classifier: Programming Language :: Python :: 3.7
Classifier: License :: OSI Approved :: GNU General Public License v3 (GPLv3)
License-File: LICENSE
Requires-Dist: pip ==23.3.1
Requires-Dist: wheel ==0.41.3
Requires-Dist: twine ==4.0.2
Requires-Dist: pyzotero ==1.5.18
